apkpure.py
apkpure-1.0.1.dist-info/LICENSE
apkpure-1.0.1.dist-info/METADATA
apkpure-1.0.1.dist-info/WHEEL
apkpure-1.0.1.dist-info/top_level.txt
apkpure-1.0.1.dist-info/RECORD
