Metadata-Version: 2.1
Name: apkpure
Version: 1.0.1
Summary: An API for interacting with the APK Pure website, allowing you to search for apps, retrieve app information, and download apps programmatically.
Author-email: Anis Homsy <anisfhomsi@gmail.com>
Project-URL: Homepage, https://github.com/anishomsy/apkpure
Project-URL: Issues, https://github.com/anishomsy/apkpure/issues
Classifier: Programming Language :: Python :: 3
Classifier: License :: OSI Approved :: Apache Software License
Classifier: Operating System :: OS Independent
Requires-Python: >=3.8
License-File: LICENSE
Requires-Dist: beautifulsoup4 >=4.12.3
Requires-Dist: requests >=2.32.3
Requires-Dist: tqdm >=4.66.4
